wireless_localization_frs_uofu/__init__.py
wireless_localization_frs_uofu/datasets.py
wireless_localization_frs_uofu/registry.py
wireless_localization_frs_uofu/utils.py
wireless_localization_frs_uofu-0.1.2.dist-info/LICENSE
wireless_localization_frs_uofu-0.1.2.dist-info/METADATA
wireless_localization_frs_uofu-0.1.2.dist-info/WHEEL
wireless_localization_frs_uofu-0.1.2.dist-info/top_level.txt
wireless_localization_frs_uofu-0.1.2.dist-info/RECORD
