Metadata-Version: 2.2
Name: wireless_localization_frs_uofu
Version: 0.1.2
Summary: A library to fetch my dataset in JSON/CSV format.
Home-page: https://github.com/mhrafi66/wireless_localization_frs_uofu
Author: University of Utah
Author-email: mumtahinhabibrafi66@gmail.com
Classifier: Programming Language :: Python :: 3
Classifier: License :: OSI Approved :: MIT License
Classifier: Operating System :: OS Independent
Requires-Python: >=3.6
License-File: LICENSE
Requires-Dist: pandas
Requires-Dist: requests
Dynamic: author
Dynamic: author-email
Dynamic: classifier
Dynamic: description
Dynamic: description-content-type
Dynamic: home-page
Dynamic: requires-dist
Dynamic: requires-python
Dynamic: summary
